{
  "name": "כללי",
  "questions": [
    {
      "question": "הארי פוטר",
      "type": "multipleChoice"
    },
    {
      "question": "מטאל",
      "type": "multipleChoice"
    },
    {
      "question": "אנימה",
      "type": "multipleChoice"
    },
    {
      "question": "מה עדיף?",
      "type": "multipleChoice",
      "choices": ["הביטלס", "רולינג סטונס"]
    },
    {
      "question": "מה עדיף?",
      "type": "multipleChoice",
      "choices": ["כדורגל", "כדורסל"]
    },
    {
      "question": "מה עדיף?",
      "type": "multipleChoice",
      "choices": ["טניס", "פינג פונג"]
    },
    {
      "question": "מה עדיף?",
      "type": "multipleChoice",
      "choices": ["פינק פלויד", "ביונסה"]
    },
    {
      "question": "מוזיקה...",
      "type": "multipleChoice",
      "choices": ["לועזית", "ישראלית"]
    },
    {
      "question": "מה עדיף?",
      "type": "multipleChoice",
      "choices": ["ים", "בריכה"]
    },
    {
      "question": "מה עדיף?",
      "type": "multipleChoice",
      "choices": ["בית פרטי", "דירה"]
    },
    {
      "question": "מה עדיף?",
      "type": "multipleChoice",
      "choices": ["ספר", "סרט", "סדרה"]
    },
    {
      "question": "מחשב",
      "type": "multipleChoice",
      "choices": ["נייח", "נייד"]
    },
    {
      "question": "מה עדיף?",
      "type": "multipleChoice",
      "choices": ["קיץ", "סתיו", "חורף", "אביב"]
    },
    {
      "question": "מה עדיף?",
      "type": "multipleChoice",
      "choices": ["קיץ", "חורף"]
    },
    {
      "question": "לאיזה בית את/ה שייך/ת?",
      "type": "multipleChoice",
      "choices": ["גריפינדור", "סלית'רין", "רייבנקלו", "האפלפאף"]
    },
    {
      "question": "מה עדיף?",
      "type": "multipleChoice",
      "choices": ["כלב", "חתול"]
    },
    {
      "question": "מה עדיף?",
      "type": "multipleChoice",
      "choices": ["פוקימון", "דיג'ימון"]
    },
    {
      "question": "מה עדיף?",
      "type": "multipleChoice",
      "choices": ["חופשת סקי", "בטן גב"]
    },
    {
      "question": "מה עדיף?",
      "type": "multipleChoice",
      "choices": ["תל אביב", "ירושלים"]
    },
    {
      "question": "מה עדיף?",
      "type": "multipleChoice",
      "choices": ["עיר", "כפר"]
    },
    {
      "question": "מה עדיף?",
      "type": "multipleChoice",
      "choices": ["האח הגדול", "משחקי הכס"]
    },
    {
      "question": "צבא: מה עדיף?",
      "type": "multipleChoice",
      "choices": ["קל\"ב", "רחוק מהבית"]
    },
    {
      "question": "צבא: מה עדיף?",
      "type": "multipleChoice",
      "choices": ["קרבי", "ג'ובניק"]
    },
    {
      "question": "טיול אחרי צבא (או כל זמן אחר):",
      "type": "multipleChoice",
      "choices": ["המזרח", "דרום אמריקה"]
    },
    {
      "question": "מה עדיף?",
      "type": "multipleChoice",
      "choices": ["שלג", "שמש"]
    },
    {
      "question": "מה עדיף?",
      "type": "multipleChoice",
      "choices": ["עצמאי", "שכיר"]
    },
    {
      "question": "יום העצמאות...",
      "type": "multipleChoice",
      "choices": ["זיקוקים", "מנגל"]
    },
    {
      "question": "מה עדיף?",
      "type": "multipleChoice",
      "choices": ["וואטסאפ", "שיחת טלפון"]
    },
    {
      "question": "מה עדיף?",
      "type": "multipleChoice",
      "choices": ["פייסבוק", "אינסטגרם", "טיקטוק", "אחר", "אף אחד"]
    },
    {
      "question": "איזה דמות מחברים את/ה?",
      "type": "multipleChoice",
      "choices": ["רייצ'ל", "רוס", "ג'ואי", "מוניקה", "צ'נדלר", "פיבי"]
    },
    {
      "question": "זקן (beard)",
      "type": "multipleChoice"
    },
    {
      "question": "רק ביבי",
      "type": "multipleChoice"
    },
    {
      "question": "מי עדיף?",
      "type": "multipleChoice",
      "choices": ["ביבי", "בילבי"]
    },
    {
      "question": "מה עדיף?",
      "type": "multipleChoice",
      "choices": ["משחקי קופסה", "משחקי מחשב"]
    },
    {
      "question": "מה עדיף?",
      "type": "multipleChoice",
      "choices": ["אנדרואיד", "אייפון"]
    },
    {
      "question": "את/ה טיפוס של...",
      "type": "multipleChoice",
      "choices": ["בוקר", "ערב"]
    },
    {
      "question": "מקלחת...",
      "type": "multipleChoice",
      "choices": ["בבוקר", "בערב", "גם וגם"]
    },
    {
      "question": "מה עדיף?",
      "type": "multipleChoice",
      "choices": ["למצוא אהבת אמת", "לזכות במיליון דולר"]
    },
    {
      "question": "להיות או לא להיות?",
      "type": "shortAnswer"
    },
    {
      "question": "נתקעת באי בודד. מה תיקח/י איתך?",
      "type": "shortAnswer"
    },
    {
      "question": "מה הסרט דיסני האהוב עליך?",
      "type": "shortAnswer"
    },
    {
      "question": "מה החג האהוב עליך?",
      "type": "shortAnswer"
    },
    {
      "question": "היעד הבא שלך בחו\"ל",
      "type": "shortAnswer"
    }
  ]
}
